dualPortFinal.v
module dp_mem_merged (
    input clk,
    input rst,
    input enb,
    input wr,
    input rd,
    input burst,                   // Burst enable
    input [4:0] w_addr,
    input [4:0] r_addr,
    input [7:0] w_data,
    output reg [7:0] r_data
);

    integer i;
    reg [11:0] mem_bank0 [7:0];    // Bank 0: 12-bit encoded data (Hamming code)
    reg [11:0] mem_bank1 [7:0];    // Bank 1: 12-bit encoded data (Hamming code)
    reg [7:0] r_burst_data [3:0];  // Burst-read buffer
    reg error_corrected;           // Flag for error correction

    // Function to count the number of '1's in an 8-bit input
    function integer count_ones(input [7:0] data);
        integer j;
        begin
            count_ones = 0;
            for (j = 0; j < 8; j = j + 1) begin
                if (data[j]) count_ones = count_ones + 1;
            end
        end
    endfunction

    // Hamming Code Functions
    function [11:0] encode_hamming(input [7:0] data);
        reg [3:0] p; // Parity bits
        begin
            // Calculate parity bits
            p[0] = data[0] ^ data[1] ^ data[3] ^ data[4] ^ data[6];
            p[1] = data[0] ^ data[2] ^ data[3] ^ data[5] ^ data[6];
            p[2] = data[1] ^ data[2] ^ data[3] ^ data[7];
            p[3] = data[4] ^ data[5] ^ data[6] ^ data[7];
            encode_hamming = {p, data};
        end
    endfunction

    function [7:0] decode_hamming(input [11:0] code);
        reg [3:0] p, p_calc, syndrome;
        reg [7:0] data;
        begin
            p = code[11:8];
            data = code[7:0];
            p_calc[0] = data[0] ^ data[1] ^ data[3] ^ data[4] ^ data[6];
            p_calc[1] = data[0] ^ data[2] ^ data[3] ^ data[5] ^ data[6];
            p_calc[2] = data[1] ^ data[2] ^ data[3] ^ data[7];
            p_calc[3] = data[4] ^ data[5] ^ data[6] ^ data[7];
            syndrome = p ^ p_calc;

            if (syndrome != 4'b0000) begin
                data[syndrome - 1] = ~data[syndrome - 1];
                decode_hamming = {1'b1, data};
            end else begin
                decode_hamming = {1'b0, data};
            end
        end
    endfunction

    // Sequential logic for memory operations
    always @(posedge clk or posedge rst) begin
        if (rst) begin
            // Reset all memory banks and variables
            for (i = 0; i < 8; i = i + 1) begin
                mem_bank0[i] <= 12'b0;
                mem_bank1[i] <= 12'b0;
            end
            r_data <= 8'b0;
            error_corrected <= 1'b0;
        end else if (enb) begin
            if (wr && !rd) begin
                // Write operation
                if (burst) begin
                    for (i = 0; i < 4; i = i + 1) begin
                        if (w_addr[4]) // Bank 1
                            mem_bank1[w_addr[3:0] + i] <= encode_hamming(
                                (count_ones(w_data + i) > 4) ? ~(w_data + i) : (w_data + i)
                            );
                        else // Bank 0
                            mem_bank0[w_addr[3:0] + i] <= encode_hamming(
                                (count_ones(w_data + i) > 4) ? ~(w_data + i) : (w_data + i)
                            );
                    end
                end else begin
                    if (w_addr[4]) // Bank 1
                        mem_bank1[w_addr[3:0]] <= encode_hamming(
                            (count_ones(w_data) > 4) ? ~w_data : w_data
                        );
                    else // Bank 0
                        mem_bank0[w_addr[3:0]] <= encode_hamming(
                            (count_ones(w_data) > 4) ? ~w_data : w_data
                        );
                end
            end
            if (!wr && rd) begin
                if (burst) begin
                    for (i = 0; i < 4; i = i + 1) begin
                        if (r_addr[4]) // Bank 1
                            {error_corrected, r_burst_data[i]} <= decode_hamming(mem_bank1[r_addr[3:0] + i]);
                        else // Bank 0
                            {error_corrected, r_burst_data[i]} <= decode_hamming(mem_bank0[r_addr[3:0] + i]);

                        if (error_corrected)
                            $display("Error corrected at address %d", r_addr + i);
                    end
                end else begin
                    if (r_addr[4]) // Bank 1
                        {error_corrected, r_data} <= decode_hamming(mem_bank1[r_addr[3:0]]);
                    else // Bank 0
                        {error_corrected, r_data} <= decode_hamming(mem_bank0[r_addr[3:0]]);

                    if (error_corrected)
                        $display("Error corrected at address %d", r_addr);
                end
            end
        end
    end

endmodule

dualPortFinal_tb.v
`include "dualPortFinal.v"

module tb_dp_mem_dbi;

    // Inputs
    reg clk;
    reg rst;
    reg enb;
    reg wr;
    reg rd;
    reg burst;
    reg [4:0] w_addr;
    reg [4:0] r_addr;
    reg [7:0] w_data;

    // Outputs
    wire [7:0] r_data;
    reg ram_passed; // Status flag to check test result

    // Instantiate the Unit Under Test (UUT)
    dp_mem_merged uut (
        .clk(clk),
        .rst(rst),
        .enb(enb),
        .wr(wr),
        .rd(rd),
        .burst(burst),
        .w_addr(w_addr),
        .r_addr(r_addr),
        .w_data(w_data),
        .r_data(r_data)
    );

    // Clock generation
    always #5 clk = ~clk; // 10ns clock period

    initial begin
        // Initialize inputs
        clk = 0;
        rst = 0;
        enb = 0;
        wr = 0;
        rd = 0;
        burst = 0;
        w_addr = 0;
        r_addr = 0;
        w_data = 0;
        ram_passed = 1;

        // VCD file generation
        $dumpfile("dp_mem_tb.vcd");  // Set the name of the VCD file
        $dumpvars(0, tb_dp_mem_dbi); // Dump all variables from the testbench module

        // Apply reset
        rst = 1;
        #10;
        rst = 0;
        #10;

        // Enable RAM operations
        enb = 1;

        // Test 1: Write and Read from Bank 0
        wr = 1;
        w_addr = 5'b00001;  // Write to Bank 0
        w_data = 8'b10101010; // Data to be written
        #10;
        $display("Written Data to Bank 0 at address %d: %b", w_addr, w_data);
        wr = 0;

        rd = 1;
        r_addr = 5'b00001;  // Read from Bank 0
        #10;
        $display("Read Data from Bank 0 at address %d: %b", r_addr, r_data);
        rd = 0;

        // Test 2: Write and Read from Bank 1
        wr = 1;
        w_addr = 5'b10001;  // Write to Bank 1 (MSB = 1)
        w_data = 8'b11110000; // Data to be written
        #10;
        $display("Written Data to Bank 1 at address %d: %b", w_addr, w_data);
        wr = 0;

        rd = 1;
        r_addr = 5'b10001;  // Read from Bank 1
        #10;
        $display("Read Data from Bank 1 at address %d: %b", r_addr, r_data);
        rd = 0;

        // Test 3: Burst Write to Bank 0
        wr = 1;
        burst = 1;
        w_addr = 5'b00000;  // Start of Bank 0
        w_data = 8'b10101010;
        #10;
        $display("Burst Write: Written Data to Bank 0 at address %d: %b", w_addr, w_data);
        burst = 0;
        wr = 0;

        // Test 4: Burst Read from Bank 0
        rd = 1;
        burst = 1;
        r_addr = 5'b00000;  // Start of Bank 0
        #40; // Allow time for burst reads
        $display("Burst Read: Read Data from Bank 0 at address %d: %b", r_addr, r_data);
        rd = 0;
        burst = 0;

        // Test 5: Burst Write to Bank 1
        wr = 1;
        burst = 1;
        w_addr = 5'b10000;  // Start of Bank 1
        w_data = 8'b11001100;
        #10;
        $display("Burst Write: Written Data to Bank 1 at address %d: %b", w_addr, w_data);
        burst = 0;
        wr = 0;

        // Test 6: Burst Read from Bank 1
        rd = 1;
        burst = 1;
        r_addr = 5'b10000;  // Start of Bank 1
        #40; // Allow time for burst reads
        $display("Burst Read: Read Data from Bank 1 at address %d: %b", r_addr, r_data);
        rd = 0;
        burst = 0;

        // Test 7: Hamming Error Correction (Bank 0)
        wr = 1;
        w_addr = 5'b00001;
        w_data = 8'b11111111;
        #10;
        $display("Written Data at address %d: %b", w_addr, w_data);
        wr = 0;

        // Introduce error in Bank 0
        uut.mem_bank0[1][2] = ~uut.mem_bank0[1][2]; // Flip bit in Bank 0

        rd = 1;
        r_addr = 5'b00001;
        #10;
        rd = 0;
        $display("Hamming Code Correction Test:");
        $display("Read Data after Error Correction: %b, Expected: 11111111", r_data);

        // Check pass/fail status
        if (ram_passed) begin
            $display("All Tests Passed: The RAM is functioning correctly.");
        end else begin
            $display("Some Tests Failed: The RAM has issues.");
        end

        // Complete the test
        #20;
        $finish;
    end
endmodule

dp_mem_tb.vcd
$date
	Mon Dec 09 01:23:42 2024
$end
$version
	Icarus Verilog
$end
$timescale
	1s
$end
$scope module tb_dp_mem_dbi $end
$var wire 8 ! r_data [7:0] $end
$var reg 1 " burst $end
$var reg 1 # clk $end
$var reg 1 $ enb $end
$var reg 5 % r_addr [4:0] $end
$var reg 1 & ram_passed $end
$var reg 1 ' rd $end
$var reg 1 ( rst $end
$var reg 5 ) w_addr [4:0] $end
$var reg 8 * w_data [7:0] $end
$var reg 1 + wr $end
$scope module uut $end
$var wire 1 " burst $end
$var wire 1 # clk $end
$var wire 1 $ enb $end
$var wire 5 , r_addr [4:0] $end
$var wire 1 ' rd $end
$var wire 1 ( rst $end
$var wire 5 - w_addr [4:0] $end
$var wire 8 . w_data [7:0] $end
$var wire 1 + wr $end
$var reg 1 / error_corrected $end
$var reg 8 0 r_data [7:0] $end
$var integer 32 1 i [31:0] $end
$scope function count_ones $end
$var reg 8 2 data [7:0] $end
$var integer 32 3 j [31:0] $end
$upscope $end
$scope function decode_hamming $end
$var reg 12 4 code [11:0] $end
$var reg 8 5 data [7:0] $end
$var reg 4 6 p [3:0] $end
$var reg 4 7 p_calc [3:0] $end
$var reg 4 8 syndrome [3:0] $end
$upscope $end
$scope function encode_hamming $end
$var reg 8 9 data [7:0] $end
$var reg 4 : p [3:0] $end
$upscope $end
$upscope $end
$upscope $end
$enddefinitions $end
$comment Show the parameter values. $end
$dumpall
$end
#0
$dumpvars
bx :
bx 9
bx 8
bx 7
bx 6
bx 5
bx 4
bx 3
bx 2
b1000 1
b0 0
0/
b0 .
b0 -
b0 ,
0+
b0 *
b0 )
1(
0'
1&
b0 %
0$
0#
0"
b0 !
$end
#5
b1000 1
1#
#10
0#
0(
#15
1#
#20
0#
b10101010 *
b10101010 .
b1 )
b1 -
1+
1$
#25
b100 :
b10101010 9
b1000 3
b10101010 2
1#
#30
0#
b1 %
b1 ,
1'
0+
#35
b10101010 !
b10101010 0
b0 8
b100 7
b10101010 5
b100 6
b10010101010 4
1#
#40
0#
b11110000 *
b11110000 .
b10001 )
b10001 -
1+
0'
#45
b11110000 9
b1000 3
b11110000 2
1#
#50
0#
b10001 %
b10001 ,
1'
0+
#55
b11110000 !
b11110000 0
b11110000 5
b10011110000 4
1#
#60
0#
b10101010 *
b10101010 .
b0 )
b0 -
1"
1+
0'
#65
b111 :
b1010010 9
b1000 3
b10101101 2
b100 1
1#
#70
0#
b0 %
b0 ,
1'
0+
1"
#75
b111 7
b111 6
b1010010 5
b11101010010 4
b100 1
1#
#80
0#
#85
b111 7
b1010010 5
b111 6
b11101010010 4
b100 1
1#
#90
0#
#95
b111 7
b1010010 5
b111 6
b11101010010 4
b100 1
1#
#100
0#
#105
b111 7
b1010010 5
b111 6
b11101010010 4
b100 1
1#
#110
0#
b11001100 *
b11001100 .
b10000 )
b10000 -
1+
1"
0'
#115
b11 :
b110000 9
b1000 3
b11001111 2
b100 1
1#
#120
0#
b10000 %
b10000 ,
1'
0+
1"
#125
b11 7
b110000 5
b11 6
b1100110000 4
b100 1
1#
#130
0#
#135
b11 7
b110000 5
b11 6
b1100110000 4
b100 1
1#
#140
0#
#145
b11 7
b110000 5
b11 6
b1100110000 4
b100 1
1#
#150
0#
#155
b11 7
b110000 5
b11 6
b1100110000 4
b100 1
1#
#160
0#
b11111111 *
b11111111 .
b1 )
b1 -
1+
0"
0'
#165
b0 :
b0 9
b1000 3
b11111111 2
1#
#170
0#
b1 %
b1 ,
1'
0+
#175
b100100 !
b100100 0
b110 8
b110 7
b100100 5
b0 6
b100 4
1#
#180
0#
0'
