dualPortRAMWave.v
module dual_port_ram (
    input clk,               // Clock
    input rst,               // Reset signal
    input wr_en,             // Write enable for port 0
    input [7:0] data_in,     // Input data to port 0
    input [3:0] addr_in_0,   // Address for port 0
    input [3:0] addr_in_1,   // Address for port 1
    input port_en_0,         // Enable port 0
    input port_en_1,         // Enable port 1
    input [5:0] burst_len_0, // 6-bit Burst length for port 0
    input [5:0] burst_len_1, // 6-bit Burst length for port 1
    input burst_en_0,        // Burst enable for port 0
    input burst_en_1,        // Burst enable for port 1
    output [7:0] data_out_0, // Output data from port 0
    output [7:0] data_out_1, // Output data from port 1
    output reg ram_passed    // Status signal to indicate pass or fail
);

// Memory declaration
reg [7:0] ram[0:255];  // Increased memory size for DDR5 simulation

// Internal burst address counters
reg [5:0] burst_addr_0, burst_addr_1;

// Writing to the RAM with burst support
always @(posedge clk or posedge rst) begin
    if (rst) begin
        // Reset burst address counters
        burst_addr_0 <= 6'd0;
        burst_addr_1 <= 6'd0;
        ram_passed <= 1'b1;
    end else begin
        if (port_en_0 && wr_en && burst_en_0) begin
            // Write data in burst mode
            ram[addr_in_0 + burst_addr_0] <= data_in;
            burst_addr_0 <= burst_addr_0 + 1'b1;
            if (burst_addr_0 == burst_len_0 - 1) begin
                burst_addr_0 <= 6'd0; // Reset burst counter
            end
        end
        if (port_en_1 && !wr_en && burst_en_1) begin
            // Read data in burst mode
            burst_addr_1 <= burst_addr_1 + 1'b1;
            if (burst_addr_1 == burst_len_1 - 1) begin
                burst_addr_1 <= 6'd0; // Reset burst counter
            end
        end
    end
end

// Always reading from the RAM
assign data_out_0 = port_en_0 ? ram[addr_in_0] : 8'dZ;
assign data_out_1 = port_en_1 ? ram[addr_in_1] : 8'dZ;

// Check pass/fail status
always @(posedge clk or posedge rst) begin
    if (rst) begin
        ram_passed <= 1'b1;
    end else if (port_en_1 && !wr_en) begin
        if (ram[addr_in_1] !== data_out_1) begin
            ram_passed <= 1'b0; // Set fail if data read does not match
        end
    end
end

endmodule

dualPortRAMWave_tb.v
`include "dualPortRAMWave.v"

module tb;

    // Inputs
    reg clk;
    reg rst;                // Reset signal
    reg wr_en;
    reg [7:0] data_in;
    reg [3:0] addr_in_0;    // Address width set to 4 bits
    reg [3:0] addr_in_1;    // Address width set to 4 bits
    reg port_en_0;
    reg port_en_1;
    reg [5:0] burst_len_0;  // Burst length for port 0 (6-bit for larger lengths)
    reg [5:0] burst_len_1;  // Burst length for port 1 (6-bit for larger lengths)
    reg burst_en_0;         // Burst enable for port 0
    reg burst_en_1;         // Burst enable for port 1

    // Outputs
    wire [7:0] data_out_0;
    wire [7:0] data_out_1;
    wire ram_passed;        // Status output to indicate pass/fail

    integer i;

    // Instantiate the Unit Under Test (UUT)
    dual_port_ram uut (
        .clk(clk),
        .rst(rst),
        .wr_en(wr_en),
        .data_in(data_in),
        .addr_in_0(addr_in_0), 
        .addr_in_1(addr_in_1), 
        .port_en_0(port_en_0),
        .port_en_1(port_en_1),
        .burst_len_0(burst_len_0),
        .burst_len_1(burst_len_1),
        .burst_en_0(burst_en_0),
        .burst_en_1(burst_en_1),
        .data_out_0(data_out_0),
        .data_out_1(data_out_1),
        .ram_passed(ram_passed)
    );

    // Clock generation (toggle every 2.5 time units)
    always #2.5 clk = ~clk;

    initial begin
        // Initialize Inputs
        clk = 0;
        rst = 0;
        addr_in_0 = 0;
        addr_in_1 = 0;
        port_en_0 = 0;
        port_en_1 = 0;
        wr_en = 0;
        data_in = 0;
        burst_len_0 = 6'd16;  // Burst length set to 16
        burst_len_1 = 6'd16;  // Burst length set to 16
        burst_en_0 = 0;
        burst_en_1 = 0;
        
        // Initialize waveform dumping
        $dumpfile("dualPortRam_tb.vcd");
        $dumpvars(0, tb);
        
        // Apply reset
        rst = 1;
        #10;
        rst = 0;
        
        // Test Burst Write Operation
        port_en_0 = 1;
        wr_en = 1;
        burst_en_0 = 1;
        
        // Write data with burst mode
        for (i = 0; i < 16; i = i + 1) begin
            data_in = i + 1;
            addr_in_0 = i[3:0];  // Address width truncated to 4 bits
            #10;
            $display("Writing at address %d, Data: %d", addr_in_0, data_in); // Debugging write
        end
        
        wr_en = 0;
        burst_en_0 = 0;
        
        // Add delay to ensure write is complete
        #50;
        
        // Read data from port 1 with burst mode
        port_en_1 = 1;
        burst_en_1 = 1;
        
        for (i = 0; i < 16; i = i + 1) begin
            addr_in_1 = i[3:0];  // Address width truncated to 4 bits
            #10;
            $display("Reading from address %d, Data: %d", addr_in_1, data_out_1); // Debugging read
        end
        
        port_en_1 = 0;
        burst_en_1 = 0;

        // Check pass/fail status
        #10;
        if (ram_passed) begin
            $display("Test Passed: The RAM is functioning correctly.");
        end else begin
            $display("Test Failed: The RAM has issues.");
        end
        
        // End simulation
        $finish;
    end
endmodule

dualPortRam_tb.vcd
$date
	Wed Nov 20 14:26:36 2024
$end
$version
	Icarus Verilog
$end
$timescale
	1s
$end
$scope module tb $end
$var wire 1 ! ram_passed $end
$var wire 8 " data_out_1 [7:0] $end
$var wire 8 # data_out_0 [7:0] $end
$var reg 4 $ addr_in_0 [3:0] $end
$var reg 4 % addr_in_1 [3:0] $end
$var reg 1 & burst_en_0 $end
$var reg 1 ' burst_en_1 $end
$var reg 6 ( burst_len_0 [5:0] $end
$var reg 6 ) burst_len_1 [5:0] $end
$var reg 1 * clk $end
$var reg 8 + data_in [7:0] $end
$var reg 1 , port_en_0 $end
$var reg 1 - port_en_1 $end
$var reg 1 . rst $end
$var reg 1 / wr_en $end
$var integer 32 0 i [31:0] $end
$scope module uut $end
$var wire 4 1 addr_in_0 [3:0] $end
$var wire 4 2 addr_in_1 [3:0] $end
$var wire 1 & burst_en_0 $end
$var wire 1 ' burst_en_1 $end
$var wire 6 3 burst_len_0 [5:0] $end
$var wire 6 4 burst_len_1 [5:0] $end
$var wire 1 * clk $end
$var wire 8 5 data_in [7:0] $end
$var wire 1 , port_en_0 $end
$var wire 1 - port_en_1 $end
$var wire 1 . rst $end
$var wire 1 / wr_en $end
$var wire 8 6 data_out_1 [7:0] $end
$var wire 8 7 data_out_0 [7:0] $end
$var reg 6 8 burst_addr_0 [5:0] $end
$var reg 6 9 burst_addr_1 [5:0] $end
$var reg 1 ! ram_passed $end
$upscope $end
$upscope $end
$enddefinitions $end
$comment Show the parameter values. $end
$dumpall
$end
#0
$dumpvars
b0 9
b0 8
bz 7
bz 6
b0 5
b10000 4
b10000 3
b0 2
b0 1
bx 0
0/
1.
0-
0,
b0 +
0*
b10000 )
b10000 (
0'
0&
b0 %
b0 $
bz #
bz "
1!
$end
#3
1*
#6
0*
#9
1*
#10
bx #
bx 7
b1 +
b1 5
b0 0
1&
1/
1,
0.
#12
0*
#15
b1 #
b1 7
b1 8
1*
#18
0*
#20
bx #
bx 7
b1 $
b1 1
b10 +
b10 5
b1 0
#21
b10 8
1*
#24
0*
#27
b11 8
1*
#30
b10 #
b10 7
0*
b10 $
b10 1
b11 +
b11 5
b10 0
#33
b100 8
1*
#36
0*
#39
b101 8
1*
#40
b11 $
b11 1
b100 +
b100 5
b11 0
#42
0*
#45
b110 8
1*
#48
0*
#50
bx #
bx 7
b100 $
b100 1
b101 +
b101 5
b100 0
#51
b111 8
1*
#54
0*
#57
b1000 8
1*
#60
b11 #
b11 7
0*
b101 $
b101 1
b110 +
b110 5
b101 0
#63
b1001 8
1*
#66
0*
#69
b1010 8
1*
#70
b110 $
b110 1
b111 +
b111 5
b110 0
#72
0*
#75
b1011 8
1*
#78
0*
#80
bx #
bx 7
b111 $
b111 1
b1000 +
b1000 5
b111 0
#81
b1100 8
1*
#84
0*
#87
b1101 8
1*
#90
b100 #
b100 7
0*
b1000 $
b1000 1
b1001 +
b1001 5
b1000 0
#93
b1110 8
1*
#96
0*
#99
b1111 8
1*
#100
bx #
bx 7
b1001 $
b1001 1
b1010 +
b1010 5
b1001 0
#102
0*
#105
b0 8
1*
#108
0*
#110
b101 #
b101 7
b1010 $
b1010 1
b1011 +
b1011 5
b1010 0
#111
b1011 #
b1011 7
b1 8
1*
#114
0*
#117
b10 8
1*
#120
0*
b1011 $
b1011 1
b1100 +
b1100 5
b1011 0
#123
b11 8
1*
#126
0*
#129
b100 8
1*
#130
bx #
bx 7
b1100 $
b1100 1
b1101 +
b1101 5
b1100 0
#132
0*
#135
b101 8
1*
#138
0*
#140
b1100 #
b1100 7
b1101 $
b1101 1
b1110 +
b1110 5
b1101 0
#141
b110 8
1*
#144
0*
#147
b111 8
1*
#150
0*
b1110 $
b1110 1
b1111 +
b1111 5
b1110 0
#153
b1000 8
1*
#156
0*
#159
b1001 8
1*
#160
bx #
bx 7
b1111 $
b1111 1
b10000 +
b10000 5
b1111 0
#162
0*
#165
b1010 8
1*
#168
0*
#170
0&
0/
b10000 0
#171
1*
#174
0*
#177
1*
#180
0*
#183
1*
#186
0*
#189
1*
#192
0*
#195
1*
#198
0*
#201
1*
#204
0*
#207
1*
#210
0*
#213
1*
#216
0*
#219
1*
#220
b1 "
b1 6
b0 0
1'
1-
#222
0*
#225
b1 9
1*
#228
0*
#230
bx "
bx 6
b1 %
b1 2
b1 0
#231
b10 9
1*
#234
0*
#237
b11 9
1*
#240
b10 "
b10 6
0*
b10 %
b10 2
b10 0
#243
b100 9
1*
#246
0*
#249
b101 9
1*
#250
b11 %
b11 2
b11 0
#252
0*
#255
b110 9
1*
#258
0*
#260
bx "
bx 6
b100 %
b100 2
b100 0
#261
b111 9
1*
#264
0*
#267
b1000 9
1*
#270
b11 "
b11 6
0*
b101 %
b101 2
b101 0
#273
b1001 9
1*
#276
0*
#279
b1010 9
1*
#280
b110 %
b110 2
b110 0
#282
0*
#285
b1011 9
1*
#288
0*
#290
bx "
bx 6
b111 %
b111 2
b111 0
#291
b1100 9
1*
#294
0*
#297
b1101 9
1*
#300
b100 "
b100 6
0*
b1000 %
b1000 2
b1000 0
#303
b1110 9
1*
#306
0*
#309
b1111 9
1*
#310
bx "
bx 6
b1001 %
b1001 2
b1001 0
#312
0*
#315
b0 9
1*
#318
0*
#320
b1011 "
b1011 6
b1010 %
b1010 2
b1010 0
#321
b1 9
1*
#324
0*
#327
b10 9
1*
#330
0*
b1011 %
b1011 2
b1011 0
#333
b11 9
1*
#336
0*
#339
b100 9
1*
#340
bx "
bx 6
b1100 %
b1100 2
b1100 0
#342
0*
#345
b101 9
1*
#348
0*
#350
b1100 "
b1100 6
b1101 %
b1101 2
b1101 0
#351
b110 9
1*
#354
0*
#357
b111 9
1*
#360
0*
b1110 %
b1110 2
b1110 0
#363
b1000 9
1*
#366
0*
#369
b1001 9
1*
#370
bx "
bx 6
b1111 %
b1111 2
b1111 0
#372
0*
#375
b1010 9
1*
#378
0*
#380
bz "
bz 6
0'
0-
b10000 0
