defines.v
`define addr_width 6
`define data_width 32
`define depth 64

singlePortRam.v
`include "defines.v"

module ram(clk, rstn, en, addr, wr_rd, data_in, data_out, out_en);

    input clk, rstn, en, wr_rd;
    input [`data_width -1:0] data_in;
    input [`addr_width -1:0] addr;
    output reg [`data_width -1:0] data_out;
    output reg out_en;

    // Memory declaration
    reg [`data_width -1:0] mem [`depth -1:0];

    // Local variable
    integer i;

    always @(posedge clk) begin
        if (en) begin
            if (!rstn) begin
                data_out <= 0;
                out_en <= 0;
                // Memory initialization is handled in the initial block
            end
            else begin
                if (wr_rd == 1) begin  // Write operation
                    mem[addr] <= data_in;
                end
                else begin  // Read operation
                    data_out <= mem[addr];
                    out_en <= 1;
                    @(posedge clk);
                    out_en <= 0;
                end
            end
        end
        else begin
            $display("RAM is disabled");
        end
    end

    // Initial block for simulation initialization
    initial begin
        // Initialize memory with a known pattern or zero
        for (i = 0; i < (2 ** `addr_width); i = i + 1) begin
            mem[i] = 0; // Initialize to 0
        end

        // Optionally, display memory contents after initialization
        // Comment or uncomment as needed
        /*
        for (i = 0; i < (2 ** `addr_width); i = i + 1) begin
            $display("mem[%0d] = %0h", i, mem[i]);
        end
        */
    end

endmodule

singlePortRAMoptimizedTestBench.v
`include "defines.v"
`include "singlePortRam.v"

module top;
    reg clk, rstn, en, wr_rd;
    reg [`data_width - 1:0] data_in;
    reg [`addr_width - 1:0] addr;
    wire [`data_width - 1:0] data_out;
    wire out_en;
    reg [`data_width - 1:0] temp[`depth - 1:0];
    reg [`data_width - 1:0] data_out_l;
    reg [`addr_width - 1:0] addr_l;

    // Instantiate DUT
    ram dut (
        .clk(clk),
        .rstn(rstn),
        .en(en),
        .wr_rd(wr_rd), 
        .data_in(data_in), 
        .addr(addr), 
        .data_out(data_out), 
        .out_en(out_en)
    );

    initial begin
        clk = 0;
        forever #5 clk = ~clk; // Clock generation
    end

    initial begin
        en = 1;
        rstn = 0; 
        #10
        rstn = 1;
    end

    initial begin
        $dumpfile("singlePortRAMoptimized.vcd");  
        $dumpvars(0, top);
    end

    initial begin
        repeat(10) begin
            write_mem();
            #50;
            read_mem();
            comp();
        end
    end

    // Task to write to memory
    task write_mem();
        begin
            wr_rd = 1; // Write operation
            addr = $random % (2 ** `addr_width); // Ensure address is within bounds
            data_in = $random; // Generates random values for data input
            addr_l = addr; // Store the address locally
            temp[addr_l] = data_in; // Save the data into the internal memory
            $display("WRITE PACKET :: en=%b wr_rd=%b addr=%h data_in=%h", en, wr_rd, addr, data_in);
        end
    endtask

    // Task to read from memory
    task read_mem();
        begin
            wr_rd = 0; // Read operation
            addr = addr_l; // Use the address from the write operation
            wait(out_en); // Wait for the output enable signal
            data_out_l = data_out; // Capture the data output
            $display("READ PACKET :: en=%b wr_rd=%b addr=%h data_out=%h", en, wr_rd, addr, data_out);
        end
    endtask

    // Task to compare read and written values
    task comp();
        begin
            if (temp[addr_l] == data_out_l) begin
                $display("RAM is PASSED ");
                $display("temp[%h]=%h data_out_l=%h \n", addr_l, temp[addr_l], data_out_l);
            end else begin
                $display("RAM is FAILED ");
                $display("temp[%h]=%h data_out_l=%h \n", addr_l, temp[addr_l], data_out_l);
            end
        end
    endtask

    initial begin
        #1000;
        $finish;
    end

endmodule

waveform.vcd
$date
	Fri Sep 20 03:18:58 2024
$end
$version
	Icarus Verilog
$end
$timescale
	1s
$end
$scope module top $end
$var wire 1 ! out_en $end
$var wire 32 " data_out [31:0] $end
$var reg 6 # addr [5:0] $end
$var reg 6 $ addr_l [5:0] $end
$var reg 1 % clk $end
$var reg 32 & data_in [31:0] $end
$var reg 32 ' data_out_l [31:0] $end
$var reg 1 ( en $end
$var reg 1 ) rstn $end
$var reg 1 * wr_rd $end
$scope module dut $end
$var wire 6 + addr [5:0] $end
$var wire 1 % clk $end
$var wire 32 , data_in [31:0] $end
$var wire 1 ( en $end
$var wire 1 ) rstn $end
$var wire 1 * wr_rd $end
$var reg 32 - data_out [31:0] $end
$var reg 1 ! out_en $end
$var integer 32 . i [31:0] $end
$upscope $end
$scope task comp $end
$upscope $end
$scope task read_mem $end
$upscope $end
$scope task write_mem $end
$upscope $end
$upscope $end
$enddefinitions $end
$comment Show the parameter values. $end
$dumpall
$end
#0
$dumpvars
b1000000 .
bx -
b11000000100010010101111010000001 ,
b100100 +
1*
0)
1(
bx '
b11000000100010010101111010000001 &
0%
b100100 $
b100100 #
bx "
x!
$end
#5
0!
b0 "
b0 -
1%
#10
0%
1)
#15
1%
#20
0%
#25
1%
#30
0%
#35
1%
#40
0%
#45
1%
#50
0%
0*
#55
b1001 $
b10110001111100000101011001100011 &
b10110001111100000101011001100011 ,
b1001 #
b1001 +
1*
b11000000100010010101111010000001 '
1!
b11000000100010010101111010000001 "
b11000000100010010101111010000001 -
1%
#60
0%
#65
0!
1%
#70
0%
#75
1%
#80
0%
#85
1%
#90
0%
#95
1%
#100
0%
#105
b1101 $
b1000110110111111001100110001101 &
b1000110110111111001100110001101 ,
b1101 #
b1101 +
b10110001111100000101011001100011 '
1!
b10110001111100000101011001100011 "
b10110001111100000101011001100011 -
1%
1*
#110
0%
#115
0!
1%
#120
0%
#125
1%
#130
0%
#135
1%
#140
0%
#145
1%
#150
0%
#155
b100101 $
b10001001001101110101001000010010 &
b10001001001101110101001000010010 ,
b100101 #
b100101 +
b1000110110111111001100110001101 '
1!
b1000110110111111001100110001101 "
b1000110110111111001100110001101 -
1%
1*
#160
0%
#165
0!
1%
#170
0%
#175
1%
#180
0%
#185
1%
#190
0%
#195
1%
#200
0%
#205
b1 $
b110110101111100110100001101 &
b110110101111100110100001101 ,
b1 #
b1 +
b10001001001101110101001000010010 '
1!
b10001001001101110101001000010010 "
b10001001001101110101001000010010 -
1%
1*
#210
0%
#215
0!
1%
#220
0%
#225
1%
#230
0%
#235
1%
#240
0%
#245
1%
#250
0%
#255
b110110 $
b11110100011011100110100111101 &
b11110100011011100110100111101 ,
b110110 #
b110110 +
b110110101111100110100001101 '
1!
b110110101111100110100001101 "
b110110101111100110100001101 -
1%
1*
#260
0%
#265
0!
1%
#270
0%
#275
1%
#280
0%
#285
1%
#290
0%
#295
1%
#300
0%
#305
b101101 $
b1000110001011011111011110001100 &
b1000110001011011111011110001100 ,
b101101 #
b101101 +
b11110100011011100110100111101 '
1!
b11110100011011100110100111101 "
b11110100011011100110100111101 -
1%
1*
#310
0%
#315
0!
1%
#320
0%
#325
1%
#330
0%
#335
1%
#340
0%
#345
1%
#350
0%
#355
b111001 $
b11100011001101110010010011000110 &
b11100011001101110010010011000110 ,
b111001 #
b111001 +
b1000110001011011111011110001100 '
1!
b1000110001011011111011110001100 "
b1000110001011011111011110001100 -
1%
1*
#360
0%
#365
0!
1%
#370
0%
#375
1%
#380
0%
#385
1%
#390
0%
#395
1%
#400
0%
#405
b101 $
b11010101000100111101001010101010 &
b11010101000100111101001010101010 ,
b101 #
b101 +
b11100011001101110010010011000110 '
1!
b11100011001101110010010011000110 "
b11100011001101110010010011000110 -
1%
1*
#410
0%
#415
0!
1%
#420
0%
#425
1%
#430
0%
#435
1%
#440
0%
#445
1%
#450
0%
#455
b100101 $
b10111011110100100111001001110111 &
b10111011110100100111001001110111 ,
b100101 #
b100101 +
b11010101000100111101001010101010 '
1!
b11010101000100111101001010101010 "
b11010101000100111101001010101010 -
1%
1*
#460
0%
#465
0!
1%
#470
0%
#475
1%
#480
0%
#485
1%
#490
0%
#495
1%
#500
0%
#505
b10111011110100100111001001110111 '
1!
b10111011110100100111001001110111 "
b10111011110100100111001001110111 -
1%
0*
#510
0%
#515
0!
1%
#520
0%
#525
1!
1%
#530
0%
#535
0!
1%
#540
0%
#545
1!
1%
#550
0%
#555
0!
1%
#560
0%
#565
1!
1%
#570
0%
#575
0!
1%
#580
0%
#585
1!
1%
#590
0%
#595
0!
1%
#600
0%
#605
1!
1%
#610
0%
#615
0!
1%
#620
0%
#625
1!
1%
#630
0%
#635
0!
1%
#640
0%
#645
1!
1%
#650
0%
#655
0!
1%
#660
0%
#665
1!
1%
#670
0%
#675
0!
1%
#680
0%
#685
1!
1%
#690
0%
#695
0!
1%
#700
0%
#705
1!
1%
#710
0%
#715
0!
1%
#720
0%
#725
1!
1%
#730
0%
#735
0!
1%
#740
0%
#745
1!
1%
#750
0%
#755
0!
1%
#760
0%
#765
1!
1%
#770
0%
#775
0!
1%
#780
0%
#785
1!
1%
#790
0%
#795
0!
1%
#800
0%
#805
1!
1%
#810
0%
#815
0!
1%
#820
0%
#825
1!
1%
#830
0%
#835
0!
1%
#840
0%
#845
1!
1%
#850
0%
#855
0!
1%
#860
0%
#865
1!
1%
#870
0%
#875
0!
1%
#880
0%
#885
1!
1%
#890
0%
#895
0!
1%
#900
0%
#905
1!
1%
#910
0%
#915
0!
1%
#920
0%
#925
1!
1%
#930
0%
#935
0!
1%
#940
0%
#945
1!
1%
#950
0%
#955
0!
1%
#960
0%
#965
1!
1%
#970
0%
#975
0!
1%
#980
0%
#985
1!
1%
#990
0%
#995
0!
1%
